colab_client/__init__.py
colab_client/auth.py
colab_client/cli.py
colab_client/client.py
colab_client/config.py
colab_client/exceptions.py
colab_client/models.py
colab_client/py.typed
colab_client-0.1.4.dist-info/METADATA
colab_client-0.1.4.dist-info/WHEEL
colab_client-0.1.4.dist-info/entry_points.txt
colab_client-0.1.4.dist-info/licenses/LICENSE
colab_client-0.1.4.dist-info/RECORD
