Metadata-Version: 2.4
Name: colab-client
Version: 0.1.4
Summary: Python client for programmatically interacting with Google Colab
Project-URL: Homepage, https://github.com/sachnun/colab-client
Project-URL: Documentation, https://github.com/sachnun/colab-client#readme
Project-URL: Repository, https://github.com/sachnun/colab-client.git
Project-URL: Issues, https://github.com/sachnun/colab-client/issues
Author: sachnun
License: MIT
License-File: LICENSE
Keywords: google-colab,jupyter,notebook,python-client,remote-execution
Classifier: Development Status :: 4 - Beta
Classifier: Intended Audience :: Developers
Classifier: License :: OSI Approved :: MIT License
Classifier: Operating System :: OS Independent
Classifier: Programming Language :: Python :: 3
Classifier: Programming Language :: Python :: 3.10
Classifier: Programming Language :: Python :: 3.11
Classifier: Programming Language :: Python :: 3.12
Classifier: Programming Language :: Python :: 3.13
Classifier: Topic :: Software Development :: Libraries :: Python Modules
Classifier: Typing :: Typed
Requires-Python: >=3.10
Requires-Dist: google-auth-oauthlib>=1.0.0
Requires-Dist: google-auth>=2.20.0
Requires-Dist: httpx>=0.24.0
Requires-Dist: websockets>=11.0
Provides-Extra: dev
Requires-Dist: mypy>=1.0.0; extra == 'dev'
Requires-Dist: pytest-asyncio>=0.21.0; extra == 'dev'
Requires-Dist: pytest-cov>=4.0.0; extra == 'dev'
Requires-Dist: pytest>=7.0.0; extra == 'dev'
Requires-Dist: ruff>=0.1.0; extra == 'dev'
